requirements.txt
setup.py
pypi_activity/__init__.py
pypi_activity.egg-info/PKG-INFO
pypi_activity.egg-info/SOURCES.txt
pypi_activity.egg-info/dependency_links.txt
pypi_activity.egg-info/top_level.txt