Metadata-Version: 2.1
Name: pypi-activity
Version: 2020.7.1
Summary: pypi.org activity journal
Home-page: https://github.com/andrewp-as-is/pypi-activity.py
License: Unlicense
Keywords: pypi
Platform: UNKNOWN
Classifier: License :: Public Domain
Classifier: Operating System :: OS Independent
Classifier: Programming Language :: Python :: 3
